map_boxes/__init__.py
map_boxes/compute_overlap_slow.py
map_boxes-1.0.6.dist-info/METADATA
map_boxes-1.0.6.dist-info/WHEEL
map_boxes-1.0.6.dist-info/top_level.txt
map_boxes-1.0.6.dist-info/RECORD
